mkdocs_gallery/__init__.py
mkdocs_gallery/_version.py
mkdocs_gallery/backreferences.py
mkdocs_gallery/binder.py
mkdocs_gallery/docs_resolv.py
mkdocs_gallery/downloads.py
mkdocs_gallery/errors.py
mkdocs_gallery/gen_data_model.py
mkdocs_gallery/gen_gallery.py
mkdocs_gallery/gen_single.py
mkdocs_gallery/mkdocs_compatibility.py
mkdocs_gallery/notebook.py
mkdocs_gallery/plugin.py
mkdocs_gallery/py_source_parser.py
mkdocs_gallery/scrapers.py
mkdocs_gallery/sorting.py
mkdocs_gallery/utils.py
mkdocs_gallery/static/binder_badge_logo.svg
mkdocs_gallery/static/broken_example.png
mkdocs_gallery/static/broken_stamp.svg
mkdocs_gallery/static/no_image.png
mkdocs_gallery/static/sg_gallery-binder.css
mkdocs_gallery/static/sg_gallery-dataframe.css
mkdocs_gallery/static/sg_gallery-rendered-html.css
mkdocs_gallery/static/sg_gallery.css
mkdocs_gallery-0.10.3.dist-info/LICENSE
mkdocs_gallery-0.10.3.dist-info/METADATA
mkdocs_gallery-0.10.3.dist-info/WHEEL
mkdocs_gallery-0.10.3.dist-info/entry_points.txt
mkdocs_gallery-0.10.3.dist-info/top_level.txt
mkdocs_gallery-0.10.3.dist-info/RECORD
