Metadata-Version: 2.1
Name: mkdocs-gallery
Version: 0.10.3
Summary: a `mkdocs` plugin to generate example galleries from python scripts, similar to `sphinx-gallery`.
Home-page: https://github.com/smarie/mkdocs-gallery
Download-URL: https://github.com/smarie/mkdocs-gallery/tarball/0.10.3
Author: Sylvain MARIE <sylvain.marie@se.com>
License: BSD 3-Clause
Keywords: gallery web page generator figure jupyter notebook binder example code latex mkdocs sphinx
Classifier: Development Status :: 5 - Production/Stable
Classifier: Intended Audience :: Developers
Classifier: License :: OSI Approved :: BSD License
Classifier: Environment :: Plugins
Classifier: Environment :: Web Environment
Classifier: Topic :: Documentation
Classifier: Programming Language :: Python
Classifier: Programming Language :: Python :: 3.7
Classifier: Programming Language :: Python :: 3.8
Classifier: Programming Language :: Python :: 3.9
Classifier: Programming Language :: Python :: 3.10
Classifier: Programming Language :: Python :: 3.11
License-File: LICENSE
Requires-Dist: mkdocs <2,>=1
Requires-Dist: mkdocs-material
Requires-Dist: tqdm
Requires-Dist: packaging
